CHANGES.txt
MANIFEST.in
README.txt
setup.cfg
setup.py
fa/__init__.py
fa.jquery.egg-info/PKG-INFO
fa.jquery.egg-info/SOURCES.txt
fa.jquery.egg-info/dependency_links.txt
fa.jquery.egg-info/entry_points.txt
fa.jquery.egg-info/namespace_packages.txt
fa.jquery.egg-info/not-zip-safe
fa.jquery.egg-info/requires.txt
fa.jquery.egg-info/top_level.txt
fa/jquery/__init__.py
fa/jquery/app.py
fa/jquery/forms.py
fa/jquery/pylons.py
fa/jquery/pyramid.py
fa/jquery/renderers.py
fa/jquery/testing.py
fa/jquery/tests.py
fa/jquery/utils.py
fa/jquery/wsgi.py
fa/jquery/datas/countries.js
fa/jquery/jquery-ui/fa.jquery.min.css
fa/jquery/jquery-ui/fa.jquery.min.js
fa/jquery/jquery-ui/fa.resource.css
fa/jquery/jquery-ui/fa.resource.js
fa/jquery/jquery-ui/indicator.gif
fa/jquery/jquery-ui/loading.gif
fa/jquery/jquery-ui/syronex-colorpicker.gif
fa/jquery/jquery-ui/colorpicker/syronex-colorpicker.css
fa/jquery/jquery-ui/colorpicker/syronex-colorpicker.gif
fa/jquery/jquery-ui/colorpicker/syronex-colorpicker.js
fa/jquery/jquery-ui/css/global.css
fa/jquery/jquery-ui/css/jquery.asmselect.css
fa/jquery/jquery-ui/css/jquery.jgrowl.css
fa/jquery/jquery-ui/css/jquery.ui.selectmenu.css
fa/jquery/jquery-ui/css/smoothness/jquery-ui-1.8.8.custom.css
fa/jquery/jquery-ui/css/smoothness/images/ui-bg_flat_0_aaaaaa_40x100.png
fa/jquery/jquery-ui/css/smoothness/images/ui-bg_flat_75_ffffff_40x100.png
fa/jquery/jquery-ui/css/smoothness/images/ui-bg_glass_55_fbf9ee_1x400.png
fa/jquery/jquery-ui/css/smoothness/images/ui-bg_glass_65_ffffff_1x400.png
fa/jquery/jquery-ui/css/smoothness/images/ui-bg_glass_75_dadada_1x400.png
fa/jquery/jquery-ui/css/smoothness/images/ui-bg_glass_75_e6e6e6_1x400.png
fa/jquery/jquery-ui/css/smoothness/images/ui-bg_glass_95_fef1ec_1x400.png
fa/jquery/jquery-ui/css/smoothness/images/ui-bg_highlight-soft_75_cccccc_1x100.png
fa/jquery/jquery-ui/css/smoothness/images/ui-icons_222222_256x240.png
fa/jquery/jquery-ui/css/smoothness/images/ui-icons_2e83ff_256x240.png
fa/jquery/jquery-ui/css/smoothness/images/ui-icons_454545_256x240.png
fa/jquery/jquery-ui/css/smoothness/images/ui-icons_888888_256x240.png
fa/jquery/jquery-ui/css/smoothness/images/ui-icons_cd0a0a_256x240.png
fa/jquery/jquery-ui/deprecated/jquery.autocomplete.js
