Metadata-Version: 1.0
Name: fa.jquery
Version: 0.9.4
Summary: jQuery widgets for formalchemy
Home-page: http://docs.formalchemy.org/fa.jquery/index.html
Author: Gael Pasgrimaud
Author-email: gael@gawel.org
License: MIT
Keywords: jquery ajax widgets
Platform: UNKNOWN
Classifier: Programming Language :: Python
Classifier: Topic :: Software Development :: Libraries :: Python Modules
